tests/.test_analyzer.py.swp
tests/__init__.py
tests/test1.pcap
tests/test_analyzer.py
tests/test_analyzer_dpkt.py
tests/test_analyzer_scapy.py
tests/test_channel_hop.py
tests/test_deauth_attack.py
tests/test_iface.py
tests/test_orchester.py
tests/test_utils.py
tests/data/4way.pcap
tests/data/Chinese-SSID-Name.pcap
tests/data/Network_Join_Nokia_Mobile.pcap
tests/data/assoc_resp.pcap
tests/data/wep.open.system.authentication.cap
tests/data/wep.shared.key.authentication.cap
tests/data/wep_64_ptw.cap
tests/data/wpa-Induction.pcap
tests/data/wpa-psk-linksys.cap
tests/data/wpa.cap
tests/data/wpa2-psk-linksys.cap
tests/data/wpa2.eapol.cap
wifi_tools/__init__.py
wifi_tools/channel_hop.py
wifi_tools/events.py
wifi_tools/execution.py
wifi_tools/factory.py
wifi_tools/gps.py
wifi_tools/iface.py
wifi_tools/lcd.py
wifi_tools/monitor.py
wifi_tools/settings.py
wifi_tools/attack/__init__.py
wifi_tools/attack/management.py
wifi_tools/attack/twin.py
wifi_tools/scripts/__init__.py
wifi_tools/scripts/generate_kml.py
wifi_tools/scripts/import_wigle.py
wifi_tools/scripts/init_db.py
wifi_tools/scripts/manage.py
wifi_tools/scripts/pyrit_auto.py
wifi_tools/sniff/CVE20170785.py
wifi_tools/sniff/__init__.py
wifi_tools/sniff/aircrack.py
wifi_tools/sniff/analyzer.py
wifi_tools/sniff/dpkt.py
wifi_tools/sniff/impacket.py
wifi_tools/sniff/nrf24l01.py
wifi_tools/sniff/scapy_sniffer.py
wifi_tools/sniff/sniff_blue.py
wifi_tools/sniff/tcpdump.py
wifi_tools/utils/__init__.py
wifi_tools/utils/bluetooth.py
wifi_tools/utils/cookies.py
wifi_tools/utils/dot11.py
wifi_tools-0.7.dist-info/DESCRIPTION.rst
wifi_tools-0.7.dist-info/METADATA
wifi_tools-0.7.dist-info/RECORD
wifi_tools-0.7.dist-info/WHEEL
wifi_tools-0.7.dist-info/dependency_links.txt
wifi_tools-0.7.dist-info/entry_points.txt
wifi_tools-0.7.dist-info/metadata.json
wifi_tools-0.7.dist-info/top_level.txt
