Metadata-Version: 2.0
Name: wifi-tools
Version: 0.7
Summary: Wifi python scripts for raspberry pi wardriving. Supports wifi, bluetooth, nrf24
Home-page: https://github.com/pepe/wifi_tools
Author: llazzaro
Author-email: llazzaro@dc.uba.ar
License: ISCL
Keywords: wifi_tools
Platform: UNKNOWN
Classifier: Development Status :: 2 - Pre-Alpha
Classifier: Intended Audience :: Developers
Classifier: License :: OSI Approved :: ISC License (ISCL)
Classifier: Natural Language :: English
Classifier: Programming Language :: Python :: 2
Classifier: Programming Language :: Python :: 2.6
Classifier: Programming Language :: Python :: 2.7
Classifier: Programming Language :: Python :: 3
Classifier: Programming Language :: Python :: 3.3
Classifier: Programming Language :: Python :: 3.4
Classifier: Programming Language :: Python :: 3.5
Requires-Dist: dpkt
Requires-Dist: pypcap
Requires-Dist: pybluez
Requires-Dist: tqdm
Requires-Dist: scapy-python3
Requires-Dist: redis
Requires-Dist: sqlalchemy
Requires-Dist: SpoofMAC
Requires-Dist: netifaces
Requires-Dist: requests
Requires-Dist: netaddr
Requires-Dist: lcubo-helpers
Requires-Dist: pyrcrack
Requires-Dist: python3-wifi
Requires-Dist: nosexcover
Requires-Dist: python-dateutil
Requires-Dist: python-nmap
Requires-Dist: multiprocessing-logging
Requires-Dist: gpsd-py3
Requires-Dist: pygpio
Requires-Dist: RPi.GPIO
Requires-Dist: char-lcd
Requires-Dist: Adafruit-GPIO
Requires-Dist: Pillow
Requires-Dist: pypcap
Requires-Dist: raspjack
